[
  {
    "NAMES": [
      "契约者"
    ],
    "DESCRIPTION": "拥有各种能力，但是使用能力之后需要支付 #y代价 ，否则一定回合后契约者会转变成 #y延迟支付者 。\n1 : 80%\n2 : 90%\n3 : 100%"
  },
  {
    "NAMES": [
      "代价"
    ],
    "DESCRIPTION": "使用 #y契约者 后产生，包含贴近剧情的减益效果。"
  },
  {
    "NAMES": [
      "延迟支付者"
    ],
    "DESCRIPTION": "无法控制自身的能力，因此费用会变成随机值。如果该阶段仍然没有支付代价，一定回合后会丧失自我。\n1 : 80%\n2 : 90%\n3 : 100%"
  },
  {
    "NAMES": [
      "人类"
    ],
    "DESCRIPTION": "普通的人类，拥有普通的能力。"
  },
  {
    "NAMES": [
      "doll"
    ],
    "DESCRIPTION": "存在天然的doll，也可以由契约者最终转换而来。无法主动打出。"
  },
  {
    "NAMES": [
      "不醉"
    ],
    "DESCRIPTION": " #y眩晕 不会被加入到抽卡堆中。"
  },
  {
    "NAMES": [
      "发胖"
    ],
    "DESCRIPTION": "没有使用的回合结束后费用+ #b1 。"
  }
]